amqtt/__init__.py
amqtt/adapters.py
amqtt/broker.py
amqtt/client.py
amqtt/codecs_amqtt.py
amqtt/contexts.py
amqtt/errors.py
amqtt/events.py
amqtt/session.py
amqtt/utils.py
amqtt/mqtt/__init__.py
amqtt/mqtt/connack.py
amqtt/mqtt/connect.py
amqtt/mqtt/constants.py
amqtt/mqtt/disconnect.py
amqtt/mqtt/packet.py
amqtt/mqtt/pingreq.py
amqtt/mqtt/pingresp.py
amqtt/mqtt/puback.py
amqtt/mqtt/pubcomp.py
amqtt/mqtt/publish.py
amqtt/mqtt/pubrec.py
amqtt/mqtt/pubrel.py
amqtt/mqtt/suback.py
amqtt/mqtt/subscribe.py
amqtt/mqtt/unsuback.py
amqtt/mqtt/unsubscribe.py
amqtt/mqtt/protocol/__init__.py
amqtt/mqtt/protocol/broker_handler.py
amqtt/mqtt/protocol/client_handler.py
amqtt/mqtt/protocol/handler.py
amqtt/plugins/__init__.py
amqtt/plugins/authentication.py
amqtt/plugins/base.py
amqtt/plugins/logging_amqtt.py
amqtt/plugins/manager.py
amqtt/plugins/persistence.py
amqtt/plugins/topic_checking.py
amqtt/plugins/sys/__init__.py
amqtt/plugins/sys/broker.py
amqtt/scripts/__init__.py
amqtt/scripts/broker_script.py
amqtt/scripts/default_broker.yaml
amqtt/scripts/default_client.yaml
amqtt/scripts/pub_script.py
amqtt/scripts/sub_script.py
amqtt-0.11.2.dist-info/METADATA
amqtt-0.11.2.dist-info/WHEEL
amqtt-0.11.2.dist-info/entry_points.txt
amqtt-0.11.2.dist-info/licenses/LICENSE.md
amqtt-0.11.2.dist-info/RECORD
