Metadata-Version: 2.4
Name: amqtt
Version: 0.11.2
Summary: Python's asyncio-native MQTT broker and client.
Author: aMQTT Contributors
License: MIT
License-File: LICENSE.md
Classifier: Development Status :: 5 - Production/Stable
Classifier: Intended Audience :: Developers
Classifier: Operating System :: MacOS
Classifier: Operating System :: Microsoft :: Windows
Classifier: Operating System :: POSIX
Classifier: Programming Language :: Python :: 3.10
Classifier: Programming Language :: Python :: 3.11
Classifier: Programming Language :: Python :: 3.12
Classifier: Programming Language :: Python :: 3.13
Classifier: Topic :: Communications
Classifier: Topic :: Internet
Requires-Python: >=3.10.0
Requires-Dist: dacite>=1.9.2
Requires-Dist: passlib==1.7.4
Requires-Dist: psutil>=7.0.0
Requires-Dist: pyyaml==6.0.2
Requires-Dist: transitions==0.9.2
Requires-Dist: typer==0.15.4
Requires-Dist: websockets==15.0.1
Provides-Extra: ci
Requires-Dist: coveralls==4.0.1; extra == 'ci'
